lab-03/echt/sumador_1bit.v
module sumador1Bit(
    input A,B,Cin,
    output Co,So);

    wire x_ab;
    wire cout_t;
    wire a_ab;



    xor(x_ab,A,B);
    and(a_ab,A,B);
    and(cout_t,x_ab,Cin);
    or(Co, cout_t,a_ab);
    xor(So,x_ab,Cin);

endmodule

lab-03/src/sumador4Bits.v
//==========================================
//  Módulo: Sumador4Bits
//==========================================
`include "sumador_1bit.v"
module sumador4Bits (
    input  [3:0] A,
    input  [3:0] B,
    input        Cin,
    output [3:0] So,
    output       Co
);

    wire C1, C2, C3; // Cables intermedios para los acarreos

    // InstanCinaCinón de los cuatro sumadores de 1 bit
    sumador1Bit S0 (.A(A[0]), .B(B[0]), .Cin(Cin), .So(So[0]), .Co(C1));
    sumador1Bit S1 (.A(A[1]), .B(B[1]), .Cin(C1), .So(So[1]), .Co(C2));
    sumador1Bit S2 (.A(A[2]), .B(B[2]), .Cin(C2), .So(So[2]), .Co(C3));
    sumador1Bit S3 (.A(A[3]), .B(B[3]), .Cin(C3), .So(So[3]), .Co(Co));

endmodule

lab-03/src/sumador_Restador_4bit.v
`include "sumador4Bits.v"
module sumador_Restador4bit(
    input [3:0] A, B, // 2 vectores de 4 bits
    input Sel,        // 0 = suma, 1 = resta
    output [3:0] So,
    output Co
);

    wire [3:0] Bx;     
    wire [3:0] Cout;   

    // Complemento a 1 si es una resta (Sel = 1)
    assign Bx[0] = B[0] ^ Sel;
    assign Bx[1] = B[1] ^ Sel;
    assign Bx[2] = B[2] ^ Sel;
    assign Bx[3] = B[3] ^ Sel;

    // Cadena de sumadores de 1 bit
    sumador4Bits s4b (A,Bx, Sel,So,Co);

endmodule

lab-03/echt/sum_rest_top.v

`include "sumador_Restador_4bit.v"

module sum_rest_top(
    input [3:0] A, B, // 2 vectores de 4 bits
    input Sel,        // 0 = suma, 1 = resta
    output [4:0] So_final,
    output signo
);


wire [3:0] So;
wire Co_aux;
wire Co;

wire [3:0] So_inter;



sumador_Restador4bit sr4 (
    .A(A),
    .B(B),
    .Sel(Sel),
    .So(So),
    .Co(Co)
);


assign Co_aux = Sel & ~Co; 
//and(Co_aux,Sel,~Co);//Define Co_aux

sumador_Restador4bit sr2(
    .A(4'b0000),
    .B(So),
    .Sel(Co_aux),
    .So(So_inter),
    .Co()
);

assign So_final = {(Sel)?1'b0 : Co, So_inter};
assign signo = Co_aux;

endmodule

lab-03/echt/tb_sum_ret_top.v
`timescale 1ns/1ps
`include "sum_rest_top.v"
module sum_rest_top_tb;

// Entradas
reg [3:0] A;
reg [3:0] B;
reg Sel; // 0 = suma, 1 = resta

// Salidas
wire [4:0] So_final;
wire signo;

// Instancia del módulo bajo prueba (UUT)
sum_rest_top uut (
    .A(A),
    .B(B),
    .Sel(Sel),
    .So_final(So_final),
    .signo(signo)
);

integer i, j;

// Encabezado
initial begin
    $display("============================================================");
    $display("     Testbench para sum_rest_top (4-bit adder/subtractor)   ");
    $display("============================================================");
    $display("  Tiempo | Sel |   A   |   B   | So_final | Signo ");
    $display("------------------------------------------------------------");
end

// Bloque de estímulos
initial begin
    // Recorre todas las combinaciones posibles de A y B
    for (Sel = 0; Sel <= 1; Sel = Sel + 1) begin
        for (i = 0; i < 16; i = i + 1) begin
            for (j = 0; j < 16; j = j + 1) begin
                A = i;
                B = j;
                #5; // pequeño retardo
                $display("%8t |  %b  | %4b | %4b |   %5b  |   %b",
                         $time, Sel, A, B, So_final, signo);
            end
        end
    end

    $display("------------------------------------------------------------");
    $finish;
end

// Opción: volcado de señales para GTKWave
initial begin
    $dumpfile("sum_rest_top_tb.vcd");
    $dumpvars(0, sum_rest_top_tb);
end

endmodule

build/sum_rest_top_tb.vcd
$date
	Wed Oct 29 12:33:22 2025
$end
$version
	Icarus Verilog
$end
$timescale
	1ps
$end
$scope module sum_rest_top_tb $end
$var wire 1 ! signo $end
$var wire 5 " So_final [4:0] $end
$var reg 4 # A [3:0] $end
$var reg 4 $ B [3:0] $end
$var reg 1 % Sel $end
$var integer 32 & i [31:0] $end
$var integer 32 ' j [31:0] $end
$scope module uut $end
$var wire 4 ( A [3:0] $end
$var wire 4 ) B [3:0] $end
$var wire 1 * Co_aux $end
$var wire 1 % Sel $end
$var wire 1 ! signo $end
$var wire 4 + So_inter [3:0] $end
$var wire 5 , So_final [4:0] $end
$var wire 4 - So [3:0] $end
$var wire 1 . Co $end
$scope module sr2 $end
$var wire 4 / A [3:0] $end
$var wire 1 * Sel $end
$var wire 4 0 So [3:0] $end
$var wire 1 1 Co $end
$var wire 4 2 Bx [3:0] $end
$var wire 4 3 B [3:0] $end
$scope module s4b $end
$var wire 4 4 A [3:0] $end
$var wire 4 5 B [3:0] $end
$var wire 1 * Cin $end
$var wire 4 6 So [3:0] $end
$var wire 1 1 Co $end
$var wire 1 7 C3 $end
$var wire 1 8 C2 $end
$var wire 1 9 C1 $end
$scope module S0 $end
$var wire 1 : A $end
$var wire 1 ; B $end
$var wire 1 * Cin $end
$var wire 1 9 Co $end
$var wire 1 < So $end
$var wire 1 = a_ab $end
$var wire 1 > cout_t $end
$var wire 1 ? x_ab $end
$upscope $end
$scope module S1 $end
$var wire 1 @ A $end
$var wire 1 A B $end
$var wire 1 9 Cin $end
$var wire 1 8 Co $end
$var wire 1 B So $end
$var wire 1 C a_ab $end
$var wire 1 D cout_t $end
$var wire 1 E x_ab $end
$upscope $end
$scope module S2 $end
$var wire 1 F A $end
$var wire 1 G B $end
$var wire 1 8 Cin $end
$var wire 1 7 Co $end
$var wire 1 H So $end
$var wire 1 I a_ab $end
$var wire 1 J cout_t $end
$var wire 1 K x_ab $end
$upscope $end
$scope module S3 $end
$var wire 1 L A $end
$var wire 1 M B $end
$var wire 1 7 Cin $end
$var wire 1 1 Co $end
$var wire 1 N So $end
$var wire 1 O a_ab $end
$var wire 1 P cout_t $end
$var wire 1 Q x_ab $end
$upscope $end
$upscope $end
$upscope $end
$scope module sr4 $end
$var wire 4 R A [3:0] $end
$var wire 4 S B [3:0] $end
$var wire 1 % Sel $end
$var wire 4 T So [3:0] $end
$var wire 1 . Co $end
$var wire 4 U Bx [3:0] $end
$scope module s4b $end
$var wire 4 V A [3:0] $end
$var wire 4 W B [3:0] $end
$var wire 1 % Cin $end
$var wire 4 X So [3:0] $end
$var wire 1 . Co $end
$var wire 1 Y C3 $end
$var wire 1 Z C2 $end
$var wire 1 [ C1 $end
$scope module S0 $end
$var wire 1 \ A $end
$var wire 1 ] B $end
$var wire 1 % Cin $end
$var wire 1 [ Co $end
$var wire 1 ^ So $end
$var wire 1 _ a_ab $end
$var wire 1 ` cout_t $end
$var wire 1 a x_ab $end
$upscope $end
$scope module S1 $end
$var wire 1 b A $end
$var wire 1 c B $end
$var wire 1 [ Cin $end
$var wire 1 Z Co $end
$var wire 1 d So $end
$var wire 1 e a_ab $end
$var wire 1 f cout_t $end
$var wire 1 g x_ab $end
$upscope $end
$scope module S2 $end
$var wire 1 h A $end
$var wire 1 i B $end
$var wire 1 Z Cin $end
$var wire 1 Y Co $end
$var wire 1 j So $end
$var wire 1 k a_ab $end
$var wire 1 l cout_t $end
$var wire 1 m x_ab $end
$upscope $end
$scope module S3 $end
$var wire 1 n A $end
$var wire 1 o B $end
$var wire 1 Y Cin $end
$var wire 1 . Co $end
$var wire 1 p So $end
$var wire 1 q a_ab $end
$var wire 1 r cout_t $end
$var wire 1 s x_ab $end
$upscope $end
$upscope $end
$upscope $end
$upscope $end
$upscope $end
$enddefinitions $end
$comment Show the parameter values. $end
$dumpall
$end
#0
$dumpvars
0s
0r
0q
0p
0o
0n
0m
0l
0k
0j
0i
0h
0g
0f
0e
0d
0c
0b
0a
0`
0_
0^
0]
0\
0[
0Z
0Y
b0 X
b0 W
b0 V
b0 U
b0 T
b0 S
b0 R
0Q
0P
0O
0N
0M
0L
0K
0J
0I
0H
0G
0F
0E
0D
0C
0B
0A
0@
0?
0>
0=
0<
0;
0:
09
08
07
b0 6
b0 5
b0 4
b0 3
b0 2
01
b0 0
b0 /
0.
b0 -
b0 ,
b0 +
0*
b0 )
b0 (
b0 '
b0 &
0%
b0 $
b0 #
b0 "
0!
$end
#5000
b1 "
b1 ,
b1 +
b1 0
b1 6
1<
1?
1;
b1 2
b1 5
b1 -
b1 3
b1 T
b1 X
1^
1a
1]
b1 U
b1 W
b1 $
b1 )
b1 S
b1 '
#10000
0<
b10 "
b10 ,
b10 +
b10 0
b10 6
1B
0?
1E
0;
1A
b10 2
b10 5
0^
b10 -
b10 3
b10 T
b10 X
1d
0a
1g
0]
1c
b10 U
b10 W
b10 $
b10 )
b10 S
b10 '
#15000
b11 "
b11 ,
b11 +
b11 0
b11 6
1<
1?
1;
b11 2
b11 5
b11 -
b11 3
b11 T
b11 X
1^
1a
1]
b11 U
b11 W
b11 $
b11 )
b11 S
b11 '
#20000
0<
0B
b100 "
b100 ,
b100 +
b100 0
b100 6
1H
0?
0E
1K
0;
0A
1G
b100 2
b100 5
0^
0d
b100 -
b100 3
b100 T
b100 X
1j
0a
0g
1m
0]
0c
1i
b100 U
b100 W
b100 $
b100 )
b100 S
b100 '
#25000
b101 "
b101 ,
b101 +
b101 0
b101 6
1<
1?
1;
b101 2
b101 5
b101 -
b101 3
b101 T
b101 X
1^
1a
1]
b101 U
b101 W
b101 $
b101 )
b101 S
b101 '
#30000
0<
b110 "
b110 ,
b110 +
b110 0
b110 6
1B
0?
1E
0;
1A
b110 2
b110 5
0^
b110 -
b110 3
b110 T
b110 X
1d
0a
1g
0]
1c
b110 U
b110 W
b110 $
b110 )
b110 S
b110 '
#35000
b111 "
b111 ,
b111 +
b111 0
b111 6
1<
1?
1;
b111 2
b111 5
b111 -
b111 3
b111 T
b111 X
1^
1a
1]
b111 U
b111 W
b111 $
b111 )
b111 S
b111 '
#40000
0<
0B
0H
b1000 "
b1000 ,
b1000 +
b1000 0
b1000 6
1N
0?
0E
0K
1Q
0;
0A
0G
1M
b1000 2
b1000 5
0^
0d
0j
b1000 -
b1000 3
b1000 T
b1000 X
1p
0a
0g
0m
1s
0]
0c
0i
1o
b1000 U
b1000 W
b1000 $
b1000 )
b1000 S
b1000 '
#45000
b1001 "
b1001 ,
b1001 +
b1001 0
b1001 6
1<
1?
1;
b1001 2
b1001 5
b1001 -
b1001 3
b1001 T
b1001 X
1^
1a
1]
b1001 U
b1001 W
b1001 $
b1001 )
b1001 S
b1001 '
#50000
0<
b1010 "
b1010 ,
b1010 +
b1010 0
b1010 6
1B
0?
1E
0;
1A
b1010 2
b1010 5
0^
b1010 -
b1010 3
b1010 T
b1010 X
1d
0a
1g
0]
1c
b1010 U
b1010 W
b1010 $
b1010 )
b1010 S
b1010 '
#55000
b1011 "
b1011 ,
b1011 +
b1011 0
b1011 6
1<
1?
1;
b1011 2
b1011 5
b1011 -
b1011 3
b1011 T
b1011 X
1^
1a
1]
b1011 U
b1011 W
b1011 $
b1011 )
b1011 S
b1011 '
#60000
0<
0B
b1100 "
b1100 ,
b1100 +
b1100 0
b1100 6
1H
0?
0E
1K
0;
0A
1G
b1100 2
b1100 5
0^
0d
b1100 -
b1100 3
b1100 T
b1100 X
1j
0a
0g
1m
0]
0c
1i
b1100 U
b1100 W
b1100 $
b1100 )
b1100 S
b1100 '
#65000
b1101 "
b1101 ,
b1101 +
b1101 0
b1101 6
1<
1?
1;
b1101 2
b1101 5
b1101 -
b1101 3
b1101 T
b1101 X
1^
1a
1]
b1101 U
b1101 W
b1101 $
b1101 )
b1101 S
b1101 '
#70000
0<
b1110 "
b1110 ,
b1110 +
b1110 0
b1110 6
1B
0?
1E
0;
1A
b1110 2
b1110 5
0^
b1110 -
b1110 3
b1110 T
b1110 X
1d
0a
1g
0]
1c
b1110 U
b1110 W
b1110 $
b1110 )
b1110 S
b1110 '
#75000
b1111 "
b1111 ,
b1111 +
b1111 0
b1111 6
1<
1?
1;
b1111 2
b1111 5
b1111 -
b1111 3
b1111 T
b1111 X
1^
1a
1]
b1111 U
b1111 W
b1111 $
b1111 )
b1111 S
b1111 '
#80000
0H
0K
0G
0N
0Q
0B
0M
b1 "
b1 ,
b1 +
b1 0
b1 6
1<
0E
0j
1?
0A
1;
0p
b1 2
b1 5
0Z
0g
0m
0s
0f
0d
0]
0c
0i
0o
b1 -
b1 3
b1 T
b1 X
1^
0[
b0 U
b0 W
1a
0_
1\
b0 $
b0 )
b0 S
b1 #
b1 (
b1 R
b1 V
b1 &
b0 '
#85000
1B
b10 "
b10 ,
b10 +
b10 0
b10 6
0<
1E
0?
1A
0;
b10 2
b10 5
1d
b10 -
b10 3
b10 T
b10 X
0^
1[
0a
1_
1]
b1 U
b1 W
b1 $
b1 )
b1 S
b1 '
#90000
0H
0K
1<
0G
b11 "
b11 ,
b11 +
b11 0
b11 6
1B
1?
1E
1;
1A
0j
b11 2
b11 5
0Z
1^
0[
0f
b11 -
b11 3
b11 T
b11 X
1d
1a
0_
1g
0]
1c
b10 U
b10 W
b10 $
b10 )
b10 S
b10 '
#95000
1H
1K
1G
0B
b100 "
b100 ,
b100 +
b100 0
b100 6
0<
0E
0?
0A
0;
1j
b100 2
b100 5
1Z
1f
0d
b100 -
b100 3
b100 T
b100 X
0^
1[
0a
1_
1]
b11 U
b11 W
b11 $
b11 )
b11 S
b11 '
#100000
0N
0Q
1<
0B
0M
b101 "
b101 ,
b101 +
b101 0
b101 6
1H
1?
0E
1K
1;
0A
1G
0p
b101 2
b101 5
0Z
0Y
1^
0[
0f
0d
0l
b101 -
b101 3
b101 T
b101 X
1j
1a
0_
0g
1m
0]
0c
1i
b100 U
b100 W
b100 $
b100 )
b100 S
b100 '
#105000
1B
b110 "
b110 ,
b110 +
b110 0
b110 6
0<
1E
0?
1A
0;
b110 2
b110 5
1d
b110 -
b110 3
b110 T
b110 X
0^
1[
0a
1_
1]
b101 U
b101 W
b101 $
b101 )
b101 S
b101 '
#110000
0N
0Q
0M
1H
1K
1<
1G
b111 "
b111 ,
b111 +
b111 0
b111 6
1B
1?
0p
1E
1;
0Y
1A
0l
1j
b111 2
b111 5
0Z
1^
0[
0f
b111 -
b111 3
b111 T
b111 X
1d
1a
0_
1g
0]
1c
b110 U
b110 W
b110 $
b110 )
b110 S
b110 '
#115000
1N
1Q
1M
0H
0K
0G
0B
b1000 "
b1000 ,
b1000 +
b1000 0
b1000 6
0<
1p
0E
0?
1Y
0A
0;
1l
0j
b1000 2
b1000 5
1Z
1f
0d
b1000 -
b1000 3
b1000 T
b1000 X
0^
1[
0a
1_
1]
b111 U
b111 W
b111 $
b111 )
b111 S
b111 '
#120000
1<
0B
0H
b1001 +
b1001 0
b1001 6
1N
1?
0E
0K
1Q
1;
0A
0G
1M
b1001 "
b1001 ,
b1001 2
b1001 5
0Z
0Y
0.
1^
0[
0f
0d
0l
0j
0r
b1001 -
b1001 3
b1001 T
b1001 X
1p
1a
0_
0g
0m
1s
0]
0c
0i
1o
b1000 U
b1000 W
b1000 $
b1000 )
b1000 S
b1000 '
#125000
1B
b1010 "
b1010 ,
b1010 +
b1010 0
b1010 6
0<
1E
0?
1A
0;
b1010 2
b1010 5
1d
b1010 -
b1010 3
b1010 T
b1010 X
0^
1[
0a
1_
1]
b1001 U
b1001 W
b1001 $
b1001 )
b1001 S
b1001 '
#130000
0H
0K
1<
0G
b1011 "
b1011 ,
b1011 +
b1011 0
b1011 6
1B
1?
1E
1;
1A
0j
b1011 2
b1011 5
0Z
1^
0[
0f
b1011 -
b1011 3
b1011 T
b1011 X
1d
1a
0_
1g
0]
1c
b1010 U
b1010 W
b1010 $
b1010 )
b1010 S
b1010 '
#135000
1H
1K
1G
0B
b1100 "
b1100 ,
b1100 +
b1100 0
b1100 6
0<
0E
0?
0A
0;
1j
b1100 2
b1100 5
1Z
1f
0d
b1100 -
b1100 3
b1100 T
b1100 X
0^
1[
0a
1_
1]
b1011 U
b1011 W
b1011 $
b1011 )
b1011 S
b1011 '
#140000
1N
1Q
1<
0B
1M
b1101 +
b1101 0
b1101 6
1H
1?
0E
b1101 "
b1101 ,
1K
1;
0A
0.
1G
0r
1p
b1101 2
b1101 5
0Z
0Y
1^
0[
0f
0d
0l
b1101 -
b1101 3
b1101 T
b1101 X
1j
1a
0_
0g
1m
0]
0c
1i
b1100 U
b1100 W
b1100 $
b1100 )
b1100 S
b1100 '
#145000
1B
b1110 "
b1110 ,
b1110 +
b1110 0
b1110 6
0<
1E
0?
1A
0;
b1110 2
b1110 5
1d
b1110 -
b1110 3
b1110 T
b1110 X
0^
1[
0a
1_
1]
b1101 U
b1101 W
b1101 $
b1101 )
b1101 S
b1101 '
#150000
1N
1Q
1M
1H
1K
1<
0.
1G
b1111 "
b1111 ,
b1111 +
b1111 0
b1111 6
1B
1?
0r
1p
1E
1;
0Y
1A
0l
1j
b1111 2
b1111 5
0Z
1^
0[
0f
b1111 -
b1111 3
b1111 T
b1111 X
1d
1a
0_
1g
0]
1c
b1110 U
b1110 W
b1110 $
b1110 )
b1110 S
b1110 '
#155000
0N
0Q
0M
0H
0K
1.
0G
0B
b10000 "
b10000 ,
b0 +
b0 0
b0 6
0<
1r
0p
0E
0?
1Y
0A
0;
1l
0j
b0 2
b0 5
1Z
1f
0d
b0 -
b0 3
b0 T
b0 X
0^
1[
0a
1_
1]
b1111 U
b1111 W
b1111 $
b1111 )
b1111 S
b1111 '
#160000
0H
0N
0K
0Q
0G
0M
0<
b10 +
b10 0
b10 6
1B
b10 "
b10 ,
0?
1E
0Y
0.
0;
1A
0Z
0l
0j
0r
0p
b10 2
b10 5
0m
0s
0]
0c
0i
0o
0^
0[
0f
b10 -
b10 3
b10 T
b10 X
1d
b0 U
b0 W
0a
0_
1g
0e
0\
1b
b0 $
b0 )
b0 S
b10 #
b10 (
b10 R
b10 V
b10 &
b0 '
#165000
b11 "
b11 ,
b11 +
b11 0
b11 6
1<
1?
1;
b11 2
b11 5
b11 -
b11 3
b11 T
b11 X
1^
1a
1]
b1 U
b1 W
b1 $
b1 )
b1 S
b1 '
#170000
1H
0<
b100 "
b100 ,
b100 +
b100 0
b100 6
0B
1K
0?
0E
1G
0;
0A
b100 2
b100 5
1j
0^
b100 -
b100 3
b100 T
b100 X
0d
1Z
0a
0g
1e
0]
1c
b10 U
b10 W
b10 $
b10 )
b10 S
b10 '
#175000
b101 "
b101 ,
b101 +
b101 0
b101 6
1<
1?
1;
b101 2
b101 5
b101 -
b101 3
b101 T
b101 X
1^
1a
1]
b11 U
b11 W
b11 $
b11 )
b11 S
b11 '
#180000
0N
0Q
0<
1B
0M
b110 "
b110 ,
b110 +
b110 0
b110 6
1H
0?
1E
1K
0;
1A
1G
0p
b110 2
b110 5
0Y
0^
1d
0Z
0l
b110 -
b110 3
b110 T
b110 X
1j
0a
1g
0e
1m
0]
0c
1i
b100 U
b100 W
b100 $
b100 )
b100 S
b100 '
#185000
b111 "
b111 ,
b111 +
b111 0
b111 6
1<
1?
1;
b111 2
b111 5
b111 -
b111 3
b111 T
b111 X
1^
1a
1]
b101 U
b101 W
b101 $
b101 )
b101 S
b101 '
#190000
1N
1Q
1M
0H
0<
b1000 "
b1000 ,
b1000 +
b1000 0
b1000 6
0B
0K
0?
0E
0G
0;
0A
1p
b1000 2
b1000 5
1Y
1l
0j
0^
b1000 -
b1000 3
b1000 T
b1000 X
0d
1Z
0a
0g
1e
0]
1c
b110 U
b110 W
b110 $
b110 )
b110 S
b110 '
#195000
b1001 "
b1001 ,
b1001 +
b1001 0
b1001 6
1<
1?
1;
b1001 2
b1001 5
b1001 -
b1001 3
b1001 T
b1001 X
1^
1a
1]
b111 U
b111 W
b111 $
b111 )
b111 S
b111 '
#200000
0<
1B
0H
b1010 +
b1010 0
b1010 6
1N
0?
1E
0K
1Q
0;
1A
0G
1M
b1010 "
b1010 ,
b1010 2
b1010 5
0Y
0.
0^
1d
0Z
0l
0j
0r
b1010 -
b1010 3
b1010 T
b1010 X
1p
0a
1g
0e
0m
1s
0]
0c
0i
1o
b1000 U
b1000 W
b1000 $
b1000 )
b1000 S
b1000 '
#205000
b1011 "
b1011 ,
b1011 +
b1011 0
b1011 6
1<
1?
1;
b1011 2
b1011 5
b1011 -
b1011 3
b1011 T
b1011 X
1^
1a
1]
b1001 U
b1001 W
b1001 $
b1001 )
b1001 S
b1001 '
#210000
1H
0<
b1100 "
b1100 ,
b1100 +
b1100 0
b1100 6
0B
1K
0?
0E
1G
0;
0A
b1100 2
b1100 5
1j
0^
b1100 -
b1100 3
b1100 T
b1100 X
0d
1Z
0a
0g
1e
0]
1c
b1010 U
b1010 W
b1010 $
b1010 )
b1010 S
b1010 '
#215000
b1101 "
b1101 ,
b1101 +
b1101 0
b1101 6
1<
1?
1;
b1101 2
b1101 5
b1101 -
b1101 3
b1101 T
b1101 X
1^
1a
1]
b1011 U
b1011 W
b1011 $
b1011 )
b1011 S
b1011 '
#220000
1N
1Q
0<
1B
1M
b1110 +
b1110 0
b1110 6
1H
0?
1E
b1110 "
b1110 ,
1K
0;
1A
0.
1G
0r
1p
b1110 2
b1110 5
0Y
0^
1d
0Z
0l
b1110 -
b1110 3
b1110 T
b1110 X
1j
0a
1g
0e
1m
0]
0c
1i
b1100 U
b1100 W
b1100 $
b1100 )
b1100 S
b1100 '
#225000
b1111 "
b1111 ,
b1111 +
b1111 0
b1111 6
1<
1?
1;
b1111 2
b1111 5
b1111 -
b1111 3
b1111 T
b1111 X
1^
1a
1]
b1101 U
b1101 W
b1101 $
b1101 )
b1101 S
b1101 '
#230000
0N
0Q
0M
0H
0<
b0 +
b0 0
b0 6
0B
b10000 "
b10000 ,
0K
0?
0E
1.
0G
0;
0A
1r
0p
b0 2
b0 5
1Y
1l
0j
0^
b0 -
b0 3
b0 T
b0 X
0d
1Z
0a
0g
1e
0]
1c
b1110 U
b1110 W
b1110 $
b1110 )
b1110 S
b1110 '
#235000
b10001 "
b10001 ,
b1 +
b1 0
b1 6
1<
1?
1;
b1 2
b1 5
b1 -
b1 3
b1 T
b1 X
1^
1a
1]
b1111 U
b1111 W
b1111 $
b1111 )
b1111 S
b1111 '
#240000
0H
0N
0K
0Q
1B
0G
0M
b11 +
b11 0
b11 6
1<
1E
b11 "
b11 ,
1?
1A
0Y
0.
1;
0f
0Z
0l
0j
0r
0p
b11 2
b11 5
1g
0e
0m
0s
1d
0]
0c
0i
0o
b11 -
b11 3
b11 T
b11 X
1^
0[
b0 U
b0 W
1a
0_
1\
b0 $
b0 )
b0 S
b11 #
b11 (
b11 R
b11 V
b11 &
b0 '
#245000
1H
1K
1G
0B
b100 "
b100 ,
b100 +
b100 0
b100 6
0<
0E
0?
0A
0;
1j
b100 2
b100 5
1Z
1f
0d
b100 -
b100 3
b100 T
b100 X
0^
1[
0a
1_
1]
b1 U
b1 W
b1 $
b1 )
b1 S
b1 '
#250000
1<
b101 "
b101 ,
b101 +
b101 0
b101 6
0B
1?
0E
1;
0A
b101 2
b101 5
1^
0[
0f
b101 -
b101 3
b101 T
b101 X
0d
1a
0_
0g
1e
0]
1c
b10 U
b10 W
b10 $
b10 )
b10 S
b10 '
#255000
1B
b110 "
b110 ,
b110 +
b110 0
b110 6
0<
1E
0?
1A
0;
b110 2
b110 5
1d
b110 -
b110 3
b110 T
b110 X
0^
1[
0a
1_
1]
b11 U
b11 W
b11 $
b11 )
b11 S
b11 '
#260000
0N
0Q
1<
1B
0M
b111 "
b111 ,
b111 +
b111 0
b111 6
1H
1?
1E
1K
1;
1A
1G
0p
b111 2
b111 5
0Y
1^
0[
0f
1d
0Z
0l
b111 -
b111 3
b111 T
b111 X
1j
1a
0_
1g
0e
1m
0]
0c
1i
b100 U
b100 W
b100 $
b100 )
b100 S
b100 '
#265000
1N
1Q
1M
0H
0K
0G
0B
b1000 "
b1000 ,
b1000 +
b1000 0
b1000 6
0<
1p
0E
0?
1Y
0A
0;
1l
0j
b1000 2
b1000 5
1Z
1f
0d
b1000 -
b1000 3
b1000 T
b1000 X
0^
1[
0a
1_
1]
b101 U
b101 W
b101 $
b101 )
b101 S
b101 '
#270000
1<
b1001 "
b1001 ,
b1001 +
b1001 0
b1001 6
0B
1?
0E
1;
0A
b1001 2
b1001 5
1^
0[
0f
b1001 -
b1001 3
b1001 T
b1001 X
0d
1a
0_
0g
1e
0]
1c
b110 U
b110 W
b110 $
b110 )
b110 S
b110 '
#275000
1B
b1010 "
b1010 ,
b1010 +
b1010 0
b1010 6
0<
1E
0?
1A
0;
b1010 2
b1010 5
1d
b1010 -
b1010 3
b1010 T
b1010 X
0^
1[
0a
1_
1]
b111 U
b111 W
b111 $
b111 )
b111 S
b111 '
#280000
1<
1B
0H
b1011 +
b1011 0
b1011 6
1N
1?
1E
0K
1Q
1;
1A
0G
1M
b1011 "
b1011 ,
b1011 2
b1011 5
0Y
0.
1^
0[
0f
1d
0Z
0l
0j
0r
b1011 -
b1011 3
b1011 T
b1011 X
1p
1a
0_
1g
0e
0m
1s
0]
0c
0i
1o
b1000 U
b1000 W
b1000 $
b1000 )
b1000 S
b1000 '
#285000
1H
1K
1G
0B
b1100 "
b1100 ,
b1100 +
b1100 0
b1100 6
0<
0E
0?
0A
0;
1j
b1100 2
b1100 5
1Z
1f
0d
b1100 -
b1100 3
b1100 T
b1100 X
0^
1[
0a
1_
1]
b1001 U
b1001 W
b1001 $
b1001 )
b1001 S
b1001 '
#290000
1<
b1101 "
b1101 ,
b1101 +
b1101 0
b1101 6
0B
1?
0E
1;
0A
b1101 2
b1101 5
1^
0[
0f
b1101 -
b1101 3
b1101 T
b1101 X
0d
1a
0_
0g
1e
0]
1c
b1010 U
b1010 W
b1010 $
b1010 )
b1010 S
b1010 '
#295000
1B
b1110 "
b1110 ,
b1110 +
b1110 0
b1110 6
0<
1E
0?
1A
0;
b1110 2
b1110 5
1d
b1110 -
b1110 3
b1110 T
b1110 X
0^
1[
0a
1_
1]
b1011 U
b1011 W
b1011 $
b1011 )
b1011 S
b1011 '
#300000
1N
1Q
1<
1B
1M
b1111 +
b1111 0
b1111 6
1H
1?
1E
b1111 "
b1111 ,
1K
1;
1A
0.
1G
0r
1p
b1111 2
b1111 5
0Y
1^
0[
0f
1d
0Z
0l
b1111 -
b1111 3
b1111 T
b1111 X
1j
1a
0_
1g
0e
1m
0]
0c
1i
b1100 U
b1100 W
b1100 $
b1100 )
b1100 S
b1100 '
#305000
0N
0Q
0M
0H
0K
1.
0G
0B
b10000 "
b10000 ,
b0 +
b0 0
b0 6
0<
1r
0p
0E
0?
1Y
0A
0;
1l
0j
b0 2
b0 5
1Z
1f
0d
b0 -
b0 3
b0 T
b0 X
0^
1[
0a
1_
1]
b1101 U
b1101 W
b1101 $
b1101 )
b1101 S
b1101 '
#310000
1<
b10001 "
b10001 ,
b1 +
b1 0
b1 6
0B
1?
0E
1;
0A
b1 2
b1 5
1^
0[
0f
b1 -
b1 3
b1 T
b1 X
0d
1a
0_
0g
1e
0]
1c
b1110 U
b1110 W
b1110 $
b1110 )
b1110 S
b1110 '
#315000
1B
b10010 "
b10010 ,
b10 +
b10 0
b10 6
0<
1E
0?
1A
0;
b10 2
b10 5
1d
b10 -
b10 3
b10 T
b10 X
0^
1[
0a
1_
1]
b1111 U
b1111 W
b1111 $
b1111 )
b1111 S
b1111 '
#320000
0N
0Q
0M
0<
0B
b100 +
b100 0
b100 6
1H
b100 "
b100 ,
0?
0Y
0E
1K
0.
0;
0A
1G
0r
0p
b100 2
b100 5
0s
0]
0c
0i
0o
0^
0[
0f
0d
0Z
0l
b100 -
b100 3
b100 T
b100 X
1j
b0 U
b0 W
0a
0_
0g
0e
1m
0k
0\
0b
1h
b0 $
b0 )
b0 S
b100 #
b100 (
b100 R
b100 V
b100 &
b0 '
#325000
b101 "
b101 ,
b101 +
b101 0
b101 6
1<
1?
1;
b101 2
b101 5
b101 -
b101 3
b101 T
b101 X
1^
1a
1]
b1 U
b1 W
b1 $
b1 )
b1 S
b1 '
#330000
0<
b110 "
b110 ,
b110 +
b110 0
b110 6
1B
0?
1E
0;
1A
b110 2
b110 5
0^
b110 -
b110 3
b110 T
b110 X
1d
0a
1g
0]
1c
b10 U
b10 W
b10 $
b10 )
b10 S
b10 '
#335000
b111 "
b111 ,
b111 +
b111 0
b111 6
1<
1?
1;
b111 2
b111 5
b111 -
b111 3
b111 T
b111 X
1^
1a
1]
b11 U
b11 W
b11 $
b11 )
b11 S
b11 '
#340000
1N
0<
0B
b1000 "
b1000 ,
b1000 +
b1000 0
b1000 6
0H
1Q
0?
0E
0K
1M
0;
0A
0G
b1000 2
b1000 5
1p
0^
0d
b1000 -
b1000 3
b1000 T
b1000 X
0j
1Y
0a
0g
0m
1k
0]
0c
1i
b100 U
b100 W
b100 $
b100 )
b100 S
b100 '
#345000
b1001 "
b1001 ,
b1001 +
b1001 0
b1001 6
1<
1?
1;
b1001 2
b1001 5
b1001 -
b1001 3
b1001 T
b1001 X
1^
1a
1]
b101 U
b101 W
b101 $
b101 )
b101 S
b101 '
#350000
0<
b1010 "
b1010 ,
b1010 +
b1010 0
b1010 6
1B
0?
1E
0;
1A
b1010 2
b1010 5
0^
b1010 -
b1010 3
b1010 T
b1010 X
1d
0a
1g
0]
1c
b110 U
b110 W
b110 $
b110 )
b110 S
b110 '
#355000
b1011 "
b1011 ,
b1011 +
b1011 0
b1011 6
1<
1?
1;
b1011 2
b1011 5
b1011 -
b1011 3
b1011 T
b1011 X
1^
1a
1]
b111 U
b111 W
b111 $
b111 )
b111 S
b111 '
