sumador_1bit.v
module sumadorOneBit(
    input A,B,Cin,
    output Co,So);

    wire x_ab;
    wire cout_t;
    wire a_ab;



    xor(x_ab,A,B);
    and(a_ab,A,B);
    and(cout_t,x_ab,Cin);
    or(Co, cout_t,a_ab);
    xor(So,x_ab,Cin);

endmodule

lab-02/parte_2/sumador_Restador_4bit.v
module sumador_Restador4bit(
    input [3:0] A, B, //2 vectores de 4 
    input Sel,           // 0 = suma, 1 = resta
    output [3:0] s0,
    output Co
);

    wire [3:0] Bx;     
    wire [3:0] Cout;   

    // saca el complemento a 1 si es una resta (sel = 1)
    assign Bx[0] = xor(B[0], Sel);
    assign Bx[1] = xor(B[1], Sel);
    assign Bx[2] = xor(B[2], Sel);
    assign Bx[3] = xor(B[3], Sel);

    // cadena de sumaodres de 1 bit
    sumadorOneBit sum_n0 (A[0], Bx[0], Sel, Cout[0], s0[0]);
    sumadorOneBit sum_n1 (A[1], Bx[1], Cout[0], Cout[1], s0[1]);
    sumadorOneBit sum_n2 (A[2], Bx[2], Cout[1], Cout[2], s0[2]);
    sumadorOneBit sum_n3 (A[3], Bx[3], Cout[2], Co, s0[3]);
endmodule

lab-02/parte_2/testbench_gtkW.v
`timescale 1ns/1ps

module tb_sumadorRestador4bit_prueba_gtkwave;

    reg [3:0] A, B;
    reg Sel;
    wire [3:0] s0;
    wire Co;


    sumador_Restador4bit modulo_de_prueba (
        .A(A),
        .B(B),
        .Sel(Sel),
        .s0(s0),
        .Co(Co)
    );

    integer i, j, k;


    initial begin

        $dumpfile("sumador.vcd");            // crea archivo de ondas
        $dumpvars(0, tb_sumadorRestador4bit_prueba_gtkwave); // guarda todas las señales del testbench y submódulos

        #1;
           for (k = 0; k < 2; k = k + 1) begin
                Sel = k;
                for (i = 0; i < 16; i = i + 1) begin
                    for (j = 0; j < 16; j = j + 1) begin
                                A = i;
                                B = j;
                                
                                #10;
                    end
                end
           end
                                

       

     $finish;
                    
                
           
    end

endmodule

lab-02/parte_2/sumador.vcd
$date
	Wed Oct 15 18:48:07 2025
$end
$version
	Icarus Verilog
$end
$timescale
	1ps
$end
$scope module tb_sumadorRestador4bit_prueba_gtkwave $end
$var wire 4 ! s0 [3:0] $end
$var wire 1 " Co $end
$var reg 4 # A [3:0] $end
$var reg 4 $ B [3:0] $end
$var reg 1 % Sel $end
$var integer 32 & i [31:0] $end
$var integer 32 ' j [31:0] $end
$var integer 32 ( k [31:0] $end
$scope module modulo_de_prueba $end
$var wire 4 ) A [3:0] $end
$var wire 4 * B [3:0] $end
$var wire 1 % Sel $end
$var wire 4 + s0 [3:0] $end
$var wire 4 , Cout [3:0] $end
$var wire 1 " Co $end
$var wire 4 - Bx [3:0] $end
$scope module sum_n0 $end
$var wire 1 . A $end
$var wire 1 / B $end
$var wire 1 % Cin $end
$var wire 1 0 Co $end
$var wire 1 1 So $end
$var wire 1 2 a_ab $end
$var wire 1 3 cout_t $end
$var wire 1 4 x_ab $end
$upscope $end
$scope module sum_n1 $end
$var wire 1 5 A $end
$var wire 1 6 B $end
$var wire 1 7 Cin $end
$var wire 1 8 Co $end
$var wire 1 9 So $end
$var wire 1 : a_ab $end
$var wire 1 ; cout_t $end
$var wire 1 < x_ab $end
$upscope $end
$scope module sum_n2 $end
$var wire 1 = A $end
$var wire 1 > B $end
$var wire 1 ? Cin $end
$var wire 1 @ Co $end
$var wire 1 A So $end
$var wire 1 B a_ab $end
$var wire 1 C cout_t $end
$var wire 1 D x_ab $end
$upscope $end
$scope module sum_n3 $end
$var wire 1 E A $end
$var wire 1 F B $end
$var wire 1 G Cin $end
$var wire 1 " Co $end
$var wire 1 H So $end
$var wire 1 I a_ab $end
$var wire 1 J cout_t $end
$var wire 1 K x_ab $end
$upscope $end
$upscope $end
$upscope $end
$enddefinitions $end
$comment Show the parameter values. $end
$dumpall
$end
#0
$dumpvars
xK
xJ
xI
xH
xG
xF
xE
xD
xC
xB
xA
x@
x?
x>
x=
x<
x;
x:
x9
x8
x7
x6
x5
x4
x3
x2
x1
x0
x/
x.
bx -
bzxxx ,
bx +
bx *
bx )
bx (
bx '
bx &
x%
bx $
bx #
x"
bx !
$end
#1000
0H
0A
0G
0?
0@
0"
08
01
0C
0J
0;
b0 !
b0 +
09
04
0<
0D
0K
07
0/
06
0>
0F
bz000 ,
00
b0 -
02
0:
0B
0I
0.
05
0=
0E
03
b0 $
b0 *
b0 #
b0 )
b0 '
b0 &
0%
b0 (
#11000
b1 !
b1 +
11
14
1/
b1 -
b1 $
b1 *
b1 '
#21000
01
b10 !
b10 +
19
04
1<
0/
16
b10 -
b10 $
b10 *
b10 '
#31000
b11 !
b11 +
11
14
1/
b11 -
b11 $
b11 *
b11 '
#41000
01
09
b100 !
b100 +
1A
04
0<
1D
0/
06
1>
b100 -
b100 $
b100 *
b100 '
#51000
b101 !
b101 +
11
14
1/
b101 -
b101 $
b101 *
b101 '
#61000
01
b110 !
b110 +
19
04
1<
0/
16
b110 -
b110 $
b110 *
b110 '
#71000
b111 !
b111 +
11
14
1/
b111 -
b111 $
b111 *
b111 '
#81000
01
09
0A
b1000 !
b1000 +
1H
04
0<
0D
1K
0/
06
0>
1F
b1000 -
b1000 $
b1000 *
b1000 '
#91000
b1001 !
b1001 +
11
14
1/
b1001 -
b1001 $
b1001 *
b1001 '
#101000
01
b1010 !
b1010 +
19
04
1<
0/
16
b1010 -
b1010 $
b1010 *
b1010 '
#111000
b1011 !
b1011 +
11
14
1/
b1011 -
b1011 $
b1011 *
b1011 '
#121000
01
09
b1100 !
b1100 +
1A
04
0<
1D
0/
06
1>
b1100 -
b1100 $
b1100 *
b1100 '
#131000
b1101 !
b1101 +
11
14
1/
b1101 -
b1101 $
b1101 *
b1101 '
#141000
01
b1110 !
b1110 +
19
04
1<
0/
16
b1110 -
b1110 $
b1110 *
b1110 '
#151000
b1111 !
b1111 +
11
14
1/
b1111 -
b1111 $
b1111 *
b1111 '
#161000
09
0A
0H
0<
0D
0K
07
0/
06
0>
0F
b1 !
b1 +
11
bz000 ,
00
b0 -
14
02
1.
b0 $
b0 *
b1 #
b1 )
b1 &
b0 '
#171000
19
17
b10 !
b10 +
01
bz001 ,
10
04
12
1/
b1 -
b1 $
b1 *
b1 '
#181000
0A
0?
07
08
11
bz000 ,
00
0;
b11 !
b11 +
19
14
02
1<
0/
16
b10 -
b10 $
b10 *
b10 '
#191000
1A
1?
18
1;
09
17
b100 !
b100 +
01
bz011 ,
10
04
12
1/
b11 -
b11 $
b11 *
b11 '
#201000
0H
0?
0G
07
08
0@
11
bz000 ,
00
0;
09
0C
b101 !
b101 +
1A
14
02
0<
1D
0/
06
1>
b100 -
b100 $
b100 *
b100 '
#211000
19
17
b110 !
b110 +
01
bz001 ,
10
04
12
1/
b101 -
b101 $
b101 *
b101 '
#221000
0H
0G
0@
0C
1A
0?
07
08
11
bz000 ,
00
0;
b111 !
b111 +
19
14
02
1<
0/
16
b110 -
b110 $
b110 *
b110 '
#231000
1H
1G
1@
1C
0A
1?
18
1;
09
17
b1000 !
b1000 +
01
bz111 ,
10
04
12
1/
b111 -
b111 $
b111 *
b111 '
#241000
0?
0G
07
08
0@
0"
11
bz000 ,
00
0;
09
0C
0A
0J
b1001 !
b1001 +
1H
14
02
0<
0D
1K
0/
06
0>
1F
b1000 -
b1000 $
b1000 *
b1000 '
#251000
19
17
b1010 !
b1010 +
01
bz001 ,
10
04
12
1/
b1001 -
b1001 $
b1001 *
b1001 '
#261000
0A
0?
07
08
11
bz000 ,
00
0;
b1011 !
b1011 +
19
14
02
1<
0/
16
b1010 -
b1010 $
b1010 *
b1010 '
#271000
1A
1?
18
1;
09
17
b1100 !
b1100 +
01
bz011 ,
10
04
12
1/
b1011 -
b1011 $
b1011 *
b1011 '
#281000
0"
0J
1H
0?
0G
07
08
0@
11
bz000 ,
00
0;
09
0C
b1101 !
b1101 +
1A
14
02
0<
1D
0/
06
1>
b1100 -
b1100 $
b1100 *
b1100 '
#291000
19
17
b1110 !
b1110 +
01
bz001 ,
10
04
12
1/
b1101 -
b1101 $
b1101 *
b1101 '
#301000
0"
0J
1H
0G
0@
0C
1A
0?
07
08
11
bz000 ,
00
0;
b1111 !
b1111 +
19
14
02
1<
0/
16
b1110 -
b1110 $
b1110 *
b1110 '
#311000
1"
1J
0H
1G
1@
1C
0A
1?
18
1;
09
17
b0 !
b0 +
01
bz111 ,
10
04
12
1/
b1111 -
b1111 $
b1111 *
b1111 '
#321000
0G
0?
0@
0"
08
0C
0A
0J
0H
0D
0K
07
0/
06
0>
0F
01
bz000 ,
00
0;
b10 !
b10 +
19
b0 -
04
02
1<
0:
0.
15
b0 $
b0 *
b10 #
b10 )
b10 &
b0 '
#331000
b11 !
b11 +
11
14
1/
b1 -
b1 $
b1 *
b1 '
#341000
1A
1?
01
b100 !
b100 +
09
bz010 ,
18
04
0<
1:
0/
16
b10 -
b10 $
b10 *
b10 '
#351000
b101 !
b101 +
11
14
1/
b11 -
b11 $
b11 *
b11 '
#361000
0H
0G
0?
0@
01
19
bz000 ,
08
0C
b110 !
b110 +
1A
04
1<
0:
1D
0/
06
1>
b100 -
b100 $
b100 *
b100 '
#371000
b111 !
b111 +
11
14
1/
b101 -
b101 $
b101 *
b101 '
#381000
1H
1G
1@
1C
0A
1?
01
b1000 !
b1000 +
09
bz110 ,
18
04
0<
1:
0/
16
b110 -
b110 $
b110 *
b110 '
#391000
b1001 !
b1001 +
11
14
1/
b111 -
b111 $
b111 *
b111 '
#401000
0G
0?
0@
0"
01
19
bz000 ,
08
0C
0A
0J
b1010 !
b1010 +
1H
04
1<
0:
0D
1K
0/
06
0>
1F
b1000 -
b1000 $
b1000 *
b1000 '
#411000
b1011 !
b1011 +
11
14
1/
b1001 -
b1001 $
b1001 *
b1001 '
#421000
1A
1?
01
b1100 !
b1100 +
09
bz010 ,
18
04
0<
1:
0/
16
b1010 -
b1010 $
b1010 *
b1010 '
#431000
b1101 !
b1101 +
11
14
1/
b1011 -
b1011 $
b1011 *
b1011 '
#441000
0"
0J
1H
0G
0?
0@
01
19
bz000 ,
08
0C
b1110 !
b1110 +
1A
04
1<
0:
1D
0/
06
1>
b1100 -
b1100 $
b1100 *
b1100 '
#451000
b1111 !
b1111 +
11
14
1/
b1101 -
b1101 $
b1101 *
b1101 '
#461000
1"
1J
0H
1G
1@
1C
0A
1?
01
b0 !
b0 +
09
bz110 ,
18
04
0<
1:
0/
16
b1110 -
b1110 $
b1110 *
b1110 '
#471000
b1 !
b1 +
11
14
1/
b1111 -
b1111 $
b1111 *
b1111 '
#481000
0?
08
19
0G
0@
0"
0C
0A
0J
0H
0;
1<
0:
0D
0K
07
0/
06
0>
0F
b11 !
b11 +
11
bz000 ,
00
b0 -
14
02
1.
b0 $
b0 *
b11 #
b11 )
b11 &
b0 '
#491000
1A
1?
18
1;
09
17
b100 !
b100 +
01
bz011 ,
10
04
12
1/
b1 -
b1 $
b1 *
b1 '
#501000
07
11
bz010 ,
00
0;
b101 !
b101 +
09
14
02
0<
1:
0/
16
b10 -
b10 $
b10 *
b10 '
#511000
19
17
b110 !
b110 +
01
bz011 ,
10
04
12
1/
b11 -
b11 $
b11 *
b11 '
#521000
0H
0G
07
0?
0@
11
00
0;
19
bz000 ,
08
0C
b111 !
b111 +
1A
14
02
1<
0:
1D
0/
06
1>
b100 -
b100 $
b100 *
b100 '
#531000
1H
1G
1@
1C
0A
1?
18
1;
09
17
b1000 !
b1000 +
01
bz111 ,
10
04
12
1/
b101 -
b101 $
b101 *
b101 '
#541000
07
11
bz110 ,
00
0;
b1001 !
b1001 +
09
14
02
0<
1:
0/
16
b110 -
b110 $
b110 *
b110 '
#551000
19
17
b1010 !
b1010 +
01
bz111 ,
10
04
12
1/
b111 -
b111 $
b111 *
b111 '
#561000
0G
07
0?
0@
0"
11
00
0;
19
bz000 ,
08
0C
0A
0J
b1011 !
b1011 +
1H
14
02
1<
0:
0D
1K
0/
06
0>
1F
b1000 -
b1000 $
b1000 *
b1000 '
#571000
1A
1?
18
1;
09
17
b1100 !
b1100 +
01
bz011 ,
10
04
12
1/
b1001 -
b1001 $
b1001 *
b1001 '
#581000
07
11
bz010 ,
00
0;
b1101 !
b1101 +
09
14
02
0<
1:
0/
16
b1010 -
b1010 $
b1010 *
b1010 '
#591000
19
17
b1110 !
b1110 +
01
bz011 ,
10
04
12
1/
b1011 -
b1011 $
b1011 *
b1011 '
#601000
0"
0J
1H
0G
07
0?
0@
11
00
0;
19
bz000 ,
08
0C
b1111 !
b1111 +
1A
14
02
1<
0:
1D
0/
06
1>
b1100 -
b1100 $
b1100 *
b1100 '
#611000
1"
1J
0H
1G
1@
1C
0A
1?
18
1;
09
17
b0 !
b0 +
01
bz111 ,
10
04
12
1/
b1101 -
b1101 $
b1101 *
b1101 '
#621000
07
11
bz110 ,
00
0;
b1 !
b1 +
09
14
02
0<
1:
0/
16
b1110 -
b1110 $
b1110 *
b1110 '
#631000
19
17
b10 !
b10 +
01
bz111 ,
10
04
12
1/
b1111 -
b1111 $
b1111 *
b1111 '
#641000
0G
0"
0@
0J
0H
0K
07
0?
0/
06
0>
0F
01
00
0;
09
bz000 ,
08
0C
b100 !
b100 +
1A
b0 -
04
02
0<
0:
1D
0B
0.
05
1=
b0 $
b0 *
b100 #
b100 )
b100 &
b0 '
#651000
b101 !
b101 +
11
14
1/
b1 -
b1 $
b1 *
b1 '
#661000
01
b110 !
b110 +
19
04
1<
0/
16
b10 -
b10 $
b10 *
b10 '
#671000
b111 !
b111 +
11
14
1/
b11 -
b11 $
b11 *
b11 '
#681000
1H
1G
01
09
b1000 !
b1000 +
0A
bz100 ,
1@
04
0<
0D
1B
0/
06
1>
b100 -
b100 $
b100 *
b100 '
#691000
b1001 !
b1001 +
11
14
1/
b101 -
b101 $
b101 *
b101 '
#701000
01
b1010 !
b1010 +
19
04
1<
0/
16
b110 -
b110 $
b110 *
b110 '
#711000
b1011 !
b1011 +
11
14
1/
b111 -
b111 $
b111 *
b111 '
#721000
0G
0"
01
09
1A
bz000 ,
0@
0J
b1100 !
b1100 +
1H
04
0<
1D
0B
1K
0/
06
0>
1F
b1000 -
b1000 $
b1000 *
b1000 '
#731000
b1101 !
b1101 +
11
14
1/
b1001 -
b1001 $
b1001 *
b1001 '
#741000
01
b1110 !
b1110 +
19
04
1<
0/
16
b1010 -
b1010 $
b1010 *
b1010 '
#751000
b1111 !
b1111 +
11
14
1/
b1011 -
b1011 $
b1011 *
b1011 '
#761000
1"
1J
0H
1G
01
09
b0 !
b0 +
0A
bz100 ,
1@
04
0<
0D
1B
0/
06
1>
b1100 -
b1100 $
b1100 *
b1100 '
#771000
b1 !
b1 +
11
14
1/
b1101 -
b1101 $
b1101 *
b1101 '
#781000
01
b10 !
b10 +
19
04
1<
0/
16
b1110 -
b1110 $
b1110 *
b1110 '
#791000
b11 !
b11 +
11
14
1/
b1111 -
b1111 $
b1111 *
b1111 '
#801000
09
0G
0"
1A
0@
0J
0H
0<
1D
0B
0K
07
0/
06
0>
0F
b101 !
b101 +
11
bz000 ,
00
b0 -
14
02
1.
b0 $
b0 *
b101 #
b101 )
b101 &
b0 '
#811000
19
17
b110 !
b110 +
01
bz001 ,
10
04
12
1/
b1 -
b1 $
b1 *
b1 '
#821000
0H
0G
0@
0C
1A
0?
07
08
11
bz000 ,
00
0;
b111 !
b111 +
19
14
02
1<
0/
16
b10 -
b10 $
b10 *
b10 '
#831000
1H
1G
1@
1C
0A
1?
18
1;
09
17
b1000 !
b1000 +
01
bz111 ,
10
04
12
1/
b11 -
b11 $
b11 *
b11 '
#841000
0?
07
08
11
bz100 ,
00
0;
09
0C
b1001 !
b1001 +
0A
14
02
0<
0D
1B
0/
06
1>
b100 -
b100 $
b100 *
b100 '
#851000
19
17
b1010 !
b1010 +
01
bz101 ,
10
04
12
1/
b101 -
b101 $
b101 *
b101 '
#861000
0A
0?
07
08
11
bz100 ,
00
0;
b1011 !
b1011 +
19
14
02
1<
0/
16
b110 -
b110 $
b110 *
b110 '
#871000
1A
1?
18
1;
09
17
b1100 !
b1100 +
01
bz111 ,
10
04
12
1/
b111 -
b111 $
b111 *
b111 '
#881000
0?
07
08
0G
0"
11
00
0;
09
0C
1A
bz000 ,
0@
0J
b1101 !
b1101 +
1H
14
02
0<
1D
0B
1K
0/
06
0>
1F
b1000 -
b1000 $
b1000 *
b1000 '
#891000
19
17
b1110 !
b1110 +
01
bz001 ,
10
04
12
1/
b1001 -
b1001 $
b1001 *
b1001 '
#901000
0"
0J
1H
0G
0@
0C
1A
0?
07
08
11
bz000 ,
00
0;
b1111 !
b1111 +
19
14
02
1<
0/
16
b1010 -
b1010 $
b1010 *
b1010 '
#911000
1"
1J
0H
1G
1@
1C
0A
1?
18
1;
09
17
b0 !
b0 +
01
bz111 ,
10
04
12
1/
b1011 -
b1011 $
b1011 *
b1011 '
#921000
0?
07
08
11
bz100 ,
00
0;
09
0C
b1 !
b1 +
0A
14
02
0<
0D
1B
0/
06
1>
b1100 -
b1100 $
b1100 *
b1100 '
#931000
19
17
b10 !
b10 +
01
bz101 ,
10
04
12
1/
b1101 -
b1101 $
b1101 *
b1101 '
#941000
0A
0?
07
08
11
bz100 ,
00
0;
b11 !
b11 +
19
14
02
1<
0/
16
b1110 -
b1110 $
b1110 *
b1110 '
#951000
1A
1?
18
1;
09
17
b100 !
b100 +
01
bz111 ,
10
04
12
1/
b1111 -
b1111 $
b1111 *
b1111 '
#961000
0?
0G
0"
08
0C
1A
0@
0J
0H
1D
0B
0K
07
0/
06
0>
0F
01
bz000 ,
00
0;
b110 !
b110 +
19
b0 -
04
02
1<
0:
0.
15
b0 $
b0 *
b110 #
b110 )
b110 &
b0 '
#971000
b111 !
b111 +
11
14
1/
b1 -
b1 $
b1 *
b1 '
#981000
1H
1G
1@
1C
0A
1?
01
b1000 !
b1000 +
09
bz110 ,
18
04
0<
1:
0/
16
b10 -
b10 $
b10 *
b10 '
#991000
b1001 !
b1001 +
11
14
1/
b11 -
b11 $
b11 *
b11 '
#1001000
0?
01
19
bz100 ,
08
0C
b1010 !
b1010 +
0A
04
1<
0:
0D
1B
0/
06
1>
b100 -
b100 $
b100 *
b100 '
#1011000
b1011 !
b1011 +
11
14
1/
b101 -
b101 $
b101 *
b101 '
#1021000
1A
1?
01
b1100 !
b1100 +
09
bz110 ,
18
04
0<
1:
0/
16
b110 -
b110 $
b110 *
b110 '
#1031000
b1101 !
b1101 +
11
14
1/
b111 -
b111 $
b111 *
b111 '
#1041000
0?
0G
0"
01
19
08
0C
1A
bz000 ,
0@
0J
b1110 !
b1110 +
1H
04
1<
0:
1D
0B
1K
0/
06
0>
1F
b1000 -
b1000 $
b1000 *
b1000 '
#1051000
b1111 !
b1111 +
11
14
1/
b1001 -
b1001 $
b1001 *
b1001 '
#1061000
1"
1J
0H
1G
1@
1C
0A
1?
01
b0 !
b0 +
09
bz110 ,
18
04
0<
1:
0/
16
b1010 -
b1010 $
b1010 *
b1010 '
#1071000
b1 !
b1 +
11
14
1/
b1011 -
b1011 $
b1011 *
b1011 '
#1081000
0?
01
19
bz100 ,
08
0C
b10 !
b10 +
0A
04
1<
0:
0D
1B
0/
06
1>
b1100 -
b1100 $
b1100 *
b1100 '
#1091000
b11 !
b11 +
11
14
1/
b1101 -
b1101 $
b1101 *
b1101 '
#1101000
1A
1?
01
b100 !
b100 +
09
bz110 ,
18
04
0<
1:
0/
16
b1110 -
b1110 $
b1110 *
b1110 '
#1111000
b101 !
b101 +
11
14
1/
b1111 -
b1111 $
b1111 *
b1111 '
#1121000
0?
08
19
0G
0"
0C
1A
0@
0J
0H
0;
1<
0:
1D
0B
0K
07
0/
06
0>
0F
b111 !
b111 +
11
bz000 ,
00
b0 -
14
02
1.
b0 $
b0 *
b111 #
b111 )
b111 &
b0 '
#1131000
1H
1G
1@
1C
0A
1?
18
1;
09
17
b1000 !
b1000 +
01
bz111 ,
10
04
12
1/
b1 -
b1 $
b1 *
b1 '
#1141000
07
11
bz110 ,
00
0;
b1001 !
b1001 +
09
14
02
0<
1:
0/
16
b10 -
b10 $
b10 *
b10 '
#1151000
19
17
b1010 !
b1010 +
01
bz111 ,
10
04
12
1/
b11 -
b11 $
b11 *
b11 '
#1161000
07
0?
11
00
0;
19
bz100 ,
08
0C
b1011 !
b1011 +
0A
14
02
1<
0:
0D
1B
0/
06
1>
b100 -
b100 $
b100 *
b100 '
#1171000
1A
1?
18
1;
09
17
b1100 !
b1100 +
01
bz111 ,
10
04
12
1/
b101 -
b101 $
b101 *
b101 '
#1181000
07
11
bz110 ,
00
0;
b1101 !
b1101 +
09
14
02
0<
1:
0/
16
b110 -
b110 $
b110 *
b110 '
#1191000
19
17
b1110 !
b1110 +
01
bz111 ,
10
04
12
1/
b111 -
b111 $
b111 *
b111 '
#1201000
07
0?
0G
0"
11
00
0;
19
08
0C
1A
bz000 ,
0@
0J
b1111 !
b1111 +
1H
14
02
1<
0:
1D
0B
1K
0/
06
0>
1F
b1000 -
b1000 $
b1000 *
b1000 '
#1211000
1"
1J
0H
1G
1@
1C
0A
1?
18
1;
09
17
b0 !
b0 +
01
bz111 ,
10
04
12
1/
b1001 -
b1001 $
b1001 *
b1001 '
#1221000
07
11
bz110 ,
00
0;
b1 !
b1 +
09
14
02
0<
1:
0/
16
b1010 -
b1010 $
b1010 *
b1010 '
#1231000
19
17
b10 !
b10 +
01
bz111 ,
10
04
12
1/
b1011 -
b1011 $
b1011 *
b1011 '
#1241000
07
0?
11
00
0;
19
bz100 ,
08
0C
b11 !
b11 +
0A
14
02
1<
0:
0D
1B
0/
06
1>
b1100 -
b1100 $
b1100 *
b1100 '
#1251000
1A
1?
18
1;
09
17
b100 !
b100 +
01
bz111 ,
10
04
12
1/
b1101 -
b1101 $
b1101 *
b1101 '
#1261000
07
11
bz110 ,
00
0;
b101 !
b101 +
09
14
02
0<
1:
0/
16
b1110 -
b1110 $
b1110 *
b1110 '
#1271000
19
17
b110 !
b110 +
01
bz111 ,
10
04
12
1/
b1111 -
b1111 $
b1111 *
b1111 '
#1281000
0"
07
0?
0G
0/
06
0>
0F
01
00
0;
09
08
0C
0A
bz000 ,
0@
0J
b1000 !
b1000 +
1H
b0 -
04
02
0<
0:
0D
0B
1K
0I
0.
05
0=
1E
b0 $
b0 *
b1000 #
b1000 )
b1000 &
b0 '
#1291000
b1001 !
b1001 +
11
14
1/
b1 -
b1 $
b1 *
b1 '
#1301000
01
b1010 !
b1010 +
19
04
1<
0/
16
b10 -
b10 $
b10 *
b10 '
#1311000
b1011 !
b1011 +
11
14
1/
b11 -
b11 $
b11 *
b11 '
#1321000
01
09
b1100 !
b1100 +
1A
04
0<
1D
0/
06
1>
b100 -
b100 $
b100 *
b100 '
#1331000
b1101 !
b1101 +
11
14
1/
b101 -
b101 $
b101 *
b101 '
#1341000
01
b1110 !
b1110 +
19
04
1<
0/
16
b110 -
b110 $
b110 *
b110 '
#1351000
b1111 !
b1111 +
11
14
1/
b111 -
b111 $
b111 *
b111 '
#1361000
01
09
0A
b0 !
b0 +
0H
1"
04
0<
0D
0K
1I
0/
06
0>
1F
b1000 -
b1000 $
b1000 *
b1000 '
#1371000
b1 !
b1 +
11
14
1/
b1001 -
b1001 $
b1001 *
b1001 '
#1381000
01
b10 !
b10 +
19
04
1<
0/
16
b1010 -
b1010 $
b1010 *
b1010 '
#1391000
b11 !
b11 +
11
14
1/
b1011 -
b1011 $
b1011 *
b1011 '
#1401000
01
09
b100 !
b100 +
1A
04
0<
1D
0/
06
1>
b1100 -
b1100 $
b1100 *
b1100 '
#1411000
b101 !
b101 +
11
14
1/
b1101 -
b1101 $
b1101 *
b1101 '
#1421000
01
b110 !
b110 +
19
04
1<
0/
16
b1110 -
b1110 $
b1110 *
b1110 '
#1431000
b111 !
b111 +
11
14
1/
b1111 -
b1111 $
b1111 *
b1111 '
#1441000
09
0A
1H
0"
0<
0D
1K
0I
07
0/
06
0>
0F
b1001 !
b1001 +
11
bz000 ,
00
b0 -
14
02
1.
b0 $
b0 *
b1001 #
b1001 )
b1001 &
b0 '
#1451000
19
17
b1010 !
b1010 +
01
bz001 ,
10
04
12
1/
b1 -
b1 $
b1 *
b1 '
#1461000
0A
0?
07
08
11
bz000 ,
00
0;
b1011 !
b1011 +
19
14
02
1<
0/
16
b10 -
b10 $
b10 *
b10 '
#1471000
1A
1?
18
1;
09
17
b1100 !
b1100 +
01
bz011 ,
10
04
12
1/
b11 -
b11 $
b11 *
b11 '
#1481000
0"
0J
1H
0?
0G
07
08
0@
11
bz000 ,
00
0;
09
0C
b1101 !
b1101 +
1A
14
02
0<
1D
0/
06
1>
b100 -
b100 $
b100 *
b100 '
#1491000
19
17
b1110 !
b1110 +
01
bz001 ,
10
04
12
1/
b101 -
b101 $
b101 *
b101 '
#1501000
0"
0J
1H
0G
0@
0C
1A
0?
07
08
11
bz000 ,
00
0;
b1111 !
b1111 +
19
14
02
1<
0/
16
b110 -
b110 $
b110 *
b110 '
#1511000
1"
1J
0H
1G
1@
1C
0A
1?
18
1;
09
17
b0 !
b0 +
01
bz111 ,
10
04
12
1/
b111 -
b111 $
b111 *
b111 '
#1521000
0?
0G
07
08
0@
11
bz000 ,
00
0;
09
0C
0A
0J
b1 !
b1 +
0H
14
02
0<
0D
0K
1I
0/
06
0>
1F
b1000 -
b1000 $
b1000 *
b1000 '
#1531000
19
17
b10 !
b10 +
01
bz001 ,
10
04
12
1/
b1001 -
b1001 $
b1001 *
b1001 '
#1541000
0A
0?
07
08
11
bz000 ,
00
0;
b11 !
b11 +
19
14
02
1<
0/
16
b1010 -
b1010 $
b1010 *
b1010 '
#1551000
1A
1?
18
1;
09
17
b100 !
b100 +
01
bz011 ,
10
04
12
1/
b1011 -
b1011 $
b1011 *
b1011 '
#1561000
0H
0?
0G
07
08
0@
11
bz000 ,
00
0;
09
0C
b101 !
b101 +
1A
14
02
0<
1D
0/
06
1>
b1100 -
b1100 $
b1100 *
b1100 '
#1571000
19
17
b110 !
b110 +
01
bz001 ,
10
04
12
1/
b1101 -
b1101 $
b1101 *
b1101 '
#1581000
0H
0G
0@
0C
1A
0?
07
08
11
bz000 ,
00
0;
b111 !
b111 +
19
14
02
1<
0/
16
b1110 -
b1110 $
b1110 *
b1110 '
#1591000
1H
1G
1@
1C
0A
1?
18
1;
09
17
b1000 !
b1000 +
01
bz111 ,
10
04
12
1/
b1111 -
b1111 $
b1111 *
b1111 '
#1601000
0G
0?
0@
08
0C
0A
0J
1H
0"
0D
1K
0I
07
0/
06
0>
0F
01
bz000 ,
00
0;
b1010 !
b1010 +
19
b0 -
04
02
1<
0:
0.
15
b0 $
b0 *
b1010 #
b1010 )
b1010 &
b0 '
#1611000
b1011 !
b1011 +
11
14
1/
b1 -
b1 $
b1 *
b1 '
#1621000
1A
1?
01
b1100 !
b1100 +
09
bz010 ,
18
04
0<
1:
0/
16
b10 -
b10 $
b10 *
b10 '
#1631000
b1101 !
b1101 +
11
14
1/
b11 -
b11 $
b11 *
b11 '
#1641000
0"
0J
1H
0G
0?
0@
01
19
bz000 ,
08
0C
b1110 !
b1110 +
1A
04
1<
0:
1D
0/
06
1>
b100 -
b100 $
b100 *
b100 '
#1651000
b1111 !
b1111 +
11
14
1/
b101 -
b101 $
b101 *
b101 '
#1661000
1"
1J
0H
1G
1@
1C
0A
1?
01
b0 !
b0 +
09
bz110 ,
18
04
0<
1:
0/
16
b110 -
b110 $
b110 *
b110 '
#1671000
b1 !
b1 +
11
14
1/
b111 -
b111 $
b111 *
b111 '
#1681000
0G
0?
0@
01
19
bz000 ,
08
0C
0A
0J
b10 !
b10 +
0H
04
1<
0:
0D
0K
1I
0/
06
0>
1F
b1000 -
b1000 $
b1000 *
b1000 '
#1691000
b11 !
b11 +
11
14
1/
b1001 -
b1001 $
b1001 *
b1001 '
#1701000
1A
1?
01
b100 !
b100 +
09
bz010 ,
18
04
0<
1:
0/
16
b1010 -
b1010 $
b1010 *
b1010 '
#1711000
b101 !
b101 +
11
14
1/
b1011 -
b1011 $
b1011 *
b1011 '
#1721000
0H
0G
0?
0@
01
19
bz000 ,
08
0C
b110 !
b110 +
1A
04
1<
0:
1D
0/
06
1>
b1100 -
b1100 $
b1100 *
b1100 '
#1731000
b111 !
b111 +
11
14
1/
b1101 -
b1101 $
b1101 *
b1101 '
#1741000
1H
1G
1@
1C
0A
1?
01
b1000 !
b1000 +
09
bz110 ,
18
04
0<
1:
0/
16
b1110 -
b1110 $
b1110 *
b1110 '
#1751000
b1001 !
b1001 +
11
14
1/
b1111 -
b1111 $
b1111 *
b1111 '
#1761000
0?
08
19
0G
0@
0C
0A
0J
1H
0"
0;
1<
0:
0D
1K
0I
07
0/
06
0>
0F
b1011 !
b1011 +
11
bz000 ,
00
b0 -
14
02
1.
b0 $
b0 *
b1011 #
b1011 )
b1011 &
b0 '
#1771000
1A
1?
18
1;
09
17
b1100 !
b1100 +
01
bz011 ,
10
04
12
1/
b1 -
b1 $
b1 *
b1 '
#1781000
07
11
bz010 ,
00
0;
b1101 !
b1101 +
09
14
02
0<
1:
0/
16
b10 -
b10 $
b10 *
b10 '
#1791000
19
17
b1110 !
b1110 +
01
bz011 ,
10
04
12
1/
b11 -
b11 $
b11 *
b11 '
#1801000
0"
0J
1H
0G
07
0?
0@
11
00
0;
19
bz000 ,
08
0C
b1111 !
b1111 +
1A
14
02
1<
0:
1D
0/
06
1>
b100 -
b100 $
b100 *
b100 '
#1811000
1"
1J
0H
1G
1@
1C
0A
1?
18
1;
09
17
b0 !
b0 +
01
bz111 ,
10
04
12
1/
b101 -
b101 $
b101 *
b101 '
